<annotation>
	<folder>Images</folder>
	<filename>cucumber_030.JPG</filename>
	<path>G:\Adrian\data\Final_Images\Images\cucumber_030.JPG</path>
	<source>
		<database>Unknown</database>
	</source>
	<size>
		<width>4032</width>
		<height>3024</height>
		<depth>3</depth>
	</size>
	<segmented>0</segmented>
	<object>
		<name>cucumber</name>
		<pose>Unspecified</pose>
		<truncated>0</truncated>
		<difficult>0</difficult>
		<bndbox>
			<xmin>2446</xmin>
			<ymin>271</ymin>
			<xmax>2702</xmax>
			<ymax>1193</ymax>
		</bndbox>
	</object>
	<object>
		<name>cucumber</name>
		<pose>Unspecified</pose>
		<truncated>0</truncated>
		<difficult>0</difficult>
		<bndbox>
			<xmin>2783</xmin>
			<ymin>496</ymin>
			<xmax>2977</xmax>
			<ymax>1368</ymax>
		</bndbox>
	</object>
	<object>
		<name>cucumber</name>
		<pose>Unspecified</pose>
		<truncated>0</truncated>
		<difficult>0</difficult>
		<bndbox>
			<xmin>3783</xmin>
			<ymin>1346</ymin>
			<xmax>3871</xmax>
			<ymax>1743</ymax>
		</bndbox>
	</object>
	<object>
		<name>cucumber</name>
		<pose>Unspecified</pose>
		<truncated>0</truncated>
		<difficult>0</difficult>
		<bndbox>
			<xmin>3821</xmin>
			<ymin>1109</ymin>
			<xmax>3952</xmax>
			<ymax>1371</ymax>
		</bndbox>
	</object>
	<object>
		<name>cucumber</name>
		<pose>Unspecified</pose>
		<truncated>0</truncated>
		<difficult>0</difficult>
		<bndbox>
			<xmin>1730</xmin>
			<ymin>734</ymin>
			<xmax>1883</xmax>
			<ymax>1093</ymax>
		</bndbox>
	</object>
	<object>
		<name>cucumber</name>
		<pose>Unspecified</pose>
		<truncated>0</truncated>
		<difficult>0</difficult>
		<bndbox>
			<xmin>2167</xmin>
			<ymin>412</ymin>
			<xmax>2258</xmax>
			<ymax>656</ymax>
		</bndbox>
	</object>
</annotation>
