<annotation>
	<folder>Images</folder>
	<filename>cucumber_253.jpg</filename>
	<path>G:\Adrian\data\Final_Images\Images\cucumber_253.jpg</path>
	<source>
		<database>Unknown</database>
	</source>
	<size>
		<width>864</width>
		<height>482</height>
		<depth>3</depth>
	</size>
	<segmented>0</segmented>
	<object>
		<name>cucumber</name>
		<pose>Unspecified</pose>
		<truncated>0</truncated>
		<difficult>0</difficult>
		<bndbox>
			<xmin>22</xmin>
			<ymin>163</ymin>
			<xmax>86</xmax>
			<ymax>478</ymax>
		</bndbox>
	</object>
	<object>
		<name>cucumber</name>
		<pose>Unspecified</pose>
		<truncated>0</truncated>
		<difficult>0</difficult>
		<bndbox>
			<xmin>24</xmin>
			<ymin>278</ymin>
			<xmax>52</xmax>
			<ymax>344</ymax>
		</bndbox>
	</object>
	<object>
		<name>cucumber</name>
		<pose>Unspecified</pose>
		<truncated>0</truncated>
		<difficult>0</difficult>
		<bndbox>
			<xmin>85</xmin>
			<ymin>368</ymin>
			<xmax>118</xmax>
			<ymax>477</ymax>
		</bndbox>
	</object>
	<object>
		<name>cucumber</name>
		<pose>Unspecified</pose>
		<truncated>0</truncated>
		<difficult>0</difficult>
		<bndbox>
			<xmin>124</xmin>
			<ymin>327</ymin>
			<xmax>225</xmax>
			<ymax>427</ymax>
		</bndbox>
	</object>
</annotation>
